<?xml version = '1.0' encoding = 'UTF-8'?>
<Relation class="oracle.dbtools.crest.model.design.logical.Relation" name="Tipo_Usuario_Menu_Perfilados" directorySegmentName="seg_0" id="F6CC4C5D-28E4-49FD-D808-BB73F503C694">
<createdBy>lmolina</createdBy>
<createdTime>2021-09-09 22:23:24 UTC</createdTime>
<ownerDesignName>modelo_logico_fv</ownerDesignName>
<sourcePk>1900539E-6FFD-E763-03A6-32E07ED89A2E</sourcePk>
<identifying>false</identifying>
<optionalSource>true</optionalSource>
<optionalTarget>false</optionalTarget>
<sourceCardinality>1</sourceCardinality>
<sourceEntity>EC8A3E8C-AF6B-4B04-C1FD-4002690F5B91</sourceEntity>
<targetCardinalityString>*</targetCardinalityString>
<targetEntity>04356B40-2ECE-533A-C09F-1D90AD97B803</targetEntity>
<transferable>true</transferable>
<deleteRule>NO ACTION</deleteRule>
</Relation>